default/__init__.py
default/core.py
default-0.1.2.dist-info/DESCRIPTION.rst
default-0.1.2.dist-info/METADATA
default-0.1.2.dist-info/RECORD
default-0.1.2.dist-info/WHEEL
default-0.1.2.dist-info/metadata.json
default-0.1.2.dist-info/top_level.txt
